{"@context":"http:\/\/iiif.io\/api\/presentation\/3\/context.json","id":"https:\/\/research.ng-london.org.uk\/iiif-projects\/json\/technical-bulletin","type":"Collection","logo":"https:\/\/research.ng-london.org.uk\/ng\/graphics\/ng_logo_tr_125.png","thumbnail":[{"id":"https:\/\/research.ng-london.org.uk\/ng\/graphics\/ngtb_logo_tr_140.png","type":"Image","format":"image\/png"}],"label":{"en":["Technical Bulletin"]},"summary":{"en":["The National Gallery Technical Bulletin, first published in 1977, has achieved a leading position in the study of the materials and techniques of painting, and the scientific examination of paintings; it is essential reading for conservators, conservation scientists, art historians, collectors and curators. Drawing on the combined expertise of curators, scientists and conservators, it brings together a wealth of information about artists\u2019 materials, practices and techniques. "]},"rights":"http:\/\/rightsstatements.org\/vocab\/InC\/1.0\/","metadata":[{"label":{"en":["Manifest Author"]},"value":{"en":["Scientific Department (NG)"]}},{"label":{"en":["Related Projects"]},"value":{"en":["<a href=\"https:\/\/research.ng-london.org.uk\/iiif-projects\/json\/iiif_collection_explorer.json\">iiif_collection_explorer<\/a>","<a href=\"https:\/\/research.ng-london.org.uk\/iiif-projects\/json\/ng-projects.json\">ng-projects<\/a>"]}},{"label":{"en":["NG Technical Bulletin"]},"value":{"en":["<a href=\"https:\/\/www.nationalgallery.org.uk\/research\/research-resources\/technical-bulletin\">LINK<\/a>"]}}],"requiredStatement":{"label":{"en":["Attribution"]},"value":{"en":["2022 \u00a9 Copyright The National Gallery, London"]}},"items":[{"id":"https:\/\/research.ng-london.org.uk\/iiif-projects\/json\/vol-31.json","type":"Collection","label":{"en":["Volume 31 - Close Examination: Fakes, Mistakes and Discoveries "]},"thumbnail":[{"id":"https:\/\/research.ng-london.org.uk\/ng\/graphics\/ng_logo_tr_125.png","type":"Image","format":"image\/jpeg"}]},{"id":"https:\/\/research.ng-london.org.uk\/iiif-projects\/json\/vol-32.json","type":"Collection","label":{"en":["Volume 32 - Leonardo da Vinci: Pupil, Painter and Master"]},"thumbnail":[{"id":"https:\/\/research.ng-london.org.uk\/ng\/graphics\/ng_logo_tr_125.png","type":"Image","format":"image\/jpeg"}]},{"id":"https:\/\/research.ng-london.org.uk\/iiif-projects\/json\/vol-33.json","type":"Collection","label":{"en":["Volume 33 - Various Articles 2012 "]},"thumbnail":[{"id":"https:\/\/research.ng-london.org.uk\/ng\/graphics\/ng_logo_tr_125.png","type":"Image","format":"image\/jpeg"}]},{"id":"https:\/\/research.ng-london.org.uk\/iiif-projects\/json\/vol-34.json","type":"Collection","label":{"en":["Volume 34 - Titian's Painting Technique Before 1540"]},"thumbnail":[{"id":"https:\/\/research.ng-london.org.uk\/ng\/graphics\/ng_logo_tr_125.png","type":"Image","format":"image\/jpeg"}]},{"id":"https:\/\/research.ng-london.org.uk\/iiif-projects\/json\/vol-35.json","type":"Collection","label":{"en":["Volume 35 - Joshua Reynolds in the National Gallery and the Wallace Collection"]},"thumbnail":[{"id":"https:\/\/research.ng-london.org.uk\/ng\/graphics\/ng_logo_tr_125.png","type":"Image","format":"image\/jpeg"}]},{"id":"https:\/\/research.ng-london.org.uk\/iiif-projects\/json\/vol-36.json","type":"Collection","label":{"en":["Volume 36 - Titian's Painting Technique From 1540"]},"thumbnail":[{"id":"https:\/\/research.ng-london.org.uk\/ng\/graphics\/ng_logo_tr_125.png","type":"Image","format":"image\/jpeg"}]}]}