{"@context":"http:\/\/iiif.io\/api\/presentation\/3\/context.json","id":"https:\/\/research.ng-london.org.uk\/iiif-projects\/json\/vol-32","type":"Collection","logo":"https:\/\/research.ng-london.org.uk\/ng\/graphics\/ng_logo_tr_125.png","thumbnail":[{"id":"https:\/\/research.ng-london.org.uk\/ng\/graphics\/NGTB-32.jpg","type":"Image","format":"image\/jpg"}],"label":{"en":["Volume 32 - Leonardo da Vinci: Pupil, Painter and Master"]},"summary":{"en":["Volume 32 of the Technical Bulletin, edited by Ashok Roy."]},"rights":"http:\/\/rightsstatements.org\/vocab\/InC\/1.0\/","metadata":[{"label":{"en":["Manifest Author"]},"value":{"en":["Scientific Department (NG)"]}},{"label":{"en":["Related Projects"]},"value":{"en":["<a href=\"https:\/\/research.ng-london.org.uk\/iiif-projects\/json\/iiif_collection_explorer.json\">iiif_collection_explorer<\/a>","<a href=\"https:\/\/research.ng-london.org.uk\/iiif-projects\/json\/ng-projects.json\">ng-projects<\/a>","<a href=\"https:\/\/research.ng-london.org.uk\/iiif-projects\/json\/technical-bulletin.json\">technical-bulletin<\/a>"]}},{"label":{"en":["NG Technical Bulletin"]},"value":{"en":["<a href=\"https:\/\/www.nationalgallery.org.uk\/research\/research-resources\/technical-bulletin\">LINK<\/a>"]}},{"label":{"en":["Technical Bulletin Vol. 32"]},"value":{"en":["<a href=\"https:\/\/www.nationalgallery.org.uk\/research\/research-resources\/technical-bulletin\/technical-bulletin-volume-32\">LINK<\/a>"]}}],"requiredStatement":{"label":{"en":["Attribution"]},"value":{"en":["2022 \u00a9 Copyright The National Gallery, London"]}},"items":[{"id":"https:\/\/research.ng-london.org.uk\/iiif-projects\/json\/dunkerton2011.json","type":"Collection","label":{"en":["Leonardo in Verrocchio's Workshop: Re-examining the Technical Evidence"]},"thumbnail":[{"id":"https:\/\/research.ng-london.org.uk\/ng\/graphics\/ng_logo_tr_125.png","type":"Image","format":"image\/jpeg"}]},{"id":"https:\/\/research.ng-london.org.uk\/iiif-projects\/json\/keith_roy_morrison_schade2011.json","type":"Collection","label":{"en":["Leonardo da Vinci's 'Virgin of the Rocks': Treatment, Technique and Display"]},"thumbnail":[{"id":"https:\/\/research.ng-london.org.uk\/ng\/graphics\/ng_logo_tr_125.png","type":"Image","format":"image\/jpeg"}]},{"id":"https:\/\/research.ng-london.org.uk\/iiif-projects\/json\/billinge_syson_spring2011.json","type":"Collection","label":{"en":["Altered Angels: Two Panels from the Immaculate Conception Altarpiece once in San Francesco Grande, Milan"]},"thumbnail":[{"id":"https:\/\/research.ng-london.org.uk\/ng\/graphics\/ng_logo_tr_125.png","type":"Image","format":"image\/jpeg"}]},{"id":"https:\/\/research.ng-london.org.uk\/iiif-projects\/json\/spring_mazzotta_roy_billinge_peggie2011.json","type":"Collection","label":{"en":["Painting Practice in Milan in the 1490s: The Influence of Leonardo"]},"thumbnail":[{"id":"https:\/\/research.ng-london.org.uk\/ng\/graphics\/ng_logo_tr_125.png","type":"Image","format":"image\/jpeg"}]}]}